msi/__init__.py
msi/buildprocess.py
msi/commandmanager.py
msi/core.py
msi/customactiontype.py
msi/database.py
msi/databasescope.py
msi/native.py
msi/proertytable.py
msi/query.py
msi/queryscope.py
msi/record.py
msi/table.py
msi/tablefieldtype.py
msi/filesystem/__init__.py
msi/filesystem/directorynode.py
msi/filesystem/filenode.py
msi/filesystem/inode.py
msi/filesystem/nodemanager.py
msi/filesystem/nodetype.py
msi/wix3/__init__.py
msi/wix3/__main__.py
msi/wix3/basebuildprocess.py
msi/wix3/languagecode.py
msi/wix3/wxsfileio.py
xid_msi-0.0.34.dist-info/LICENSE
xid_msi-0.0.34.dist-info/METADATA
xid_msi-0.0.34.dist-info/WHEEL
xid_msi-0.0.34.dist-info/entry_points.txt
xid_msi-0.0.34.dist-info/top_level.txt
xid_msi-0.0.34.dist-info/RECORD
