Metadata-Version: 2.1
Name: xid-msi
Version: 0.0.34
Summary: Xidware Microsoft Installer
Home-page: https://xidware.com
Author: xidware
Author-email: developer@xidware.com
Classifier: Programming Language :: Python :: 3
Classifier: License :: OSI Approved :: MIT License
Classifier: Operating System :: OS Independent
Requires-Python: >=3.9.7
License-File: LICENSE
Requires-Dist: xid-xpl
